[
 
    {
      "id": "H-01",
      "coords": [[961.93,2070.11],[928.45,2110.77],[874.19,2066.31],[907.32,2025.57]],
      "area": "66 m²",
      "estado": "Disponible"
    },
    {
      "id": "H-02",
      "coords": [[907.95,2024.77],[929.94,1997.72],[984.64,2042.54],[962.47,2069.41]],
      "area": "66 m²",
      "estado": "Disponible"
    },
    {
      "id": "H-03",
      "coords": [[930.57,1996.76],[956.37,1965.3],[1010.97,2010.29],[985.35,2041.75]],
      "area": "66 m²",
      "estado": "Disponible"
    },
    {
      "id": "H-04",
      "coords": [[955.57,1964.93],[928.71,1942.66],[887.63,1992.86],[914.57,2014.69]],
      "area": "66 m²",
      "estado": "Disponible"
    },
    {
      "id": "H-05",
      "coords": [[927.9,1941.86],[900.78,1920.3],[859.87,1970.24],[886.91,1991.98]],
      "area": "66 m²",
      "estado": "Disponible"
    },
    {
      "id": "H-06",
      "coords": [[873.1,1897.4],[899.96,1919.5],[859.14,1969.62],[832.28,1947.52]],
      "area": "66 m²",
      "estado": "Disponible"
    },
    {
      "id": "H-07",
      "coords": [[817.78,1852.24],[795.78,1879.2],[850.21,1923.65],[872.3,1896.96]],
      "area": "66 m²",
      "estado": "Disponible"
    },
    {
      "id": "H-08",
      "coords": [[795.06,1879.81],[773.15,1906.86],[827.57,1951.41],[849.57,1924.63]],
      "area": "66 m²",
      "estado": "Disponible"
    },
    {
      "id": "H-09",
      "coords": [[772.38,1907.58],[750.26,1934.61],[805.12,1979.07],[827.04,1952.29]],
      "area": "66 m²",
      "estado": "Disponible"
    },
    {
      "id": "H-10",
      "coords": [[831.56,1948.23],[858.52,1970.24],[817.44,2020.35],[790.75,1998.25]],
      "area": "66 m²",
      "estado": "Disponible"
    },
    {
      "id": "H-11",
      "coords": [[859.41,1970.94],[886.1,1992.95],[845.19,2042.8],[818.51,2020.97]],
      "area": "66 m²",
      "estado": "Disponible"
    },
    {
      "id": "H-12",
      "coords": [[886.98,1993.48],[913.84,2015.67],[873.11,2065.52],[846.16,2043.6]],
      "area": "66 m²",
      "estado": "Disponible"
    },
    {
      "id": "H-13",
      "coords": [[794.16,2034.21],[771.38,2060.48],[820.06,2102.91],[842.96,2076.65]],
      "area": "66 m²",
      "estado": "Disponible"
    },
    {
      "id": "H-14",
      "coords": [[770.67,2061.36],[747.87,2087.53],[796.47,2129.95],[819.26,2103.79]],
      "area": "66 m²",
      "estado": "Disponible"
    },
    {
      "id": "H-15",
      "coords": [[733.62,2076.52],[710.65,2102.95],[772.85,2156.78],[795.65,2130.7]],
      "area": "66 m²",
      "estado": "Disponible"
    },
    {
      "id": "H-16",
      "coords": [[670.52,2021.77],[647.73,2047.93],[709.93,2102.11],[732.74,2075.95]],
      "area": "66 m²",
      "estado": "Disponible"
    },
    {
      "id": "H-17",
      "coords": [[713.13,1963.87],[739.28,1986.59],[692.99,2039.8],[666.74,2017.17]],
      "area": "66 m²",
      "estado": "Disponible"
    },
    {
      "id": "H-18",
      "coords": [[740.17,1987.38],[766.41,2010.19],[719.94,2063.31],[693.88,2040.68]],
      "area": "66 m²",
      "estado": "Disponible"
    },
    {
      "id": "H-19",
      "coords": [[767.13,2010.72],[793.38,2033.52],[747.08,2086.91],[720.84,2064.02]],
      "area": "66 m²",
      "estado": "Disponible"
    },
    {
      "id": "H-20",
      "coords": [[690.25,2118.29],[690.43,2153.02],[625.58,2153.02],[625.49,2118.11]],
      "area": "66 m²",
      "estado": "Disponible"
    },
    {
      "id": "H-21",
      "coords": [[702.16,2154.08],[702.16,2224.62],[667.26,2224.53],[667.26,2153.99]],
      "area": "66 m²",
      "estado": "Disponible"
    },
    {
      "id": "H-22",
      "coords": [[666.37,2154.08],[666.37,2224.62],[631.65,2224.62],[631.56,2153.99]],
      "area": "66 m²",
      "estado": "Disponible"
    },
    {
      "id": "H-23",
      "coords": [[630.41,2154.17],[630.5,2224.53],[595.69,2224.62],[595.66,2153.99]],
      "area": "66 m²",
      "estado": "Disponible"
    },
    
    {
      "id": "H-24",
      "coords": [[594.59,2154.17],[594.68,2224.62],[559.87,2224.53],[559.96,2154.08]],
      "area": "66 m²",
      "estado": "Disponible"
    },
    {
      "id": "H-25",
      "coords": [[624.55,2118.2],[624.55,2153.02],[559.87,2153.11],[559.87,2118.2]],
      "area": "66 m²",
      "estado": "Disponible"
    },
    {
      "id": "H-26",
      "coords": [[624.45,2082.65],[624.54,2117.3],[559.87,2117.3],[559.87,2082.39]],
      "area": "66 m²",
      "estado": "Disponible"
    },
    {
      "id": "H-27",
      "coords": [[534.93,2160.18],[534.93,2224.53],[500.3,2224.53],[500.2,2160]],
      "area": "66 m²",
      "estado": "Disponible"
    },
    {
      "id": "H-28",
      "coords": [[499.22,2159.92],[499.22,2224.62],[464.59,2224.62],[464.41,2159.83]],
      "area": "66 m²",
      "estado": "Disponible"
    },
    {
      "id": "H-29",
      "coords": [[463.25,2160.09],[463.34,2224.62],[428.61,2224.62],[428.61,2160.09]],
      "area": "66 m²",
      "estado": "Disponible"
    },
    {
      "id": "H-30",
      "coords": [[427.54,2160.09],[427.54,2224.53],[392.9,2224.53],[392.73,2160]],
      "area": "66 m²",
      "estado": "Disponible"
    },
    {
      "id": "H-31",
      "coords": [[391.74,2160.18],[391.74,2224.44],[356.93,2224.53],[356.84,2160]],
      "area": "66 m²",
      "estado": "Disponible"
    },
    {
      "id": "H-32",
      "coords": [[355.78,2160.18],[355.78,2224.44],[321.06,2224.62],[321.06,2160]],
      "area": "66 m²",
      "estado": "Disponible"
    },
    {
      "id": "H-33",
      "coords": [[319.97,2160.09],[319.97,2224.53],[285.25,2224.62],[285.34,2160]],
      "area": "66 m²",
      "estado": "Disponible"
    },
    {
      "id": "H-34",
      "coords": [[284.14,2160.3],[284.23,2224.56],[249.42,2224.64],[249.42,2159.94]],
      "area": "66 m²",
      "estado": "Disponible"
    },
    {
      "id": "H-35",
      "coords": [[248.29,2160.18],[248.38,2224.62],[213.75,2224.62],[213.57,2160]],
      "area": "66 m²",
      "estado": "Disponible"
    },
    {
      "id": "H-36",
      "coords": [[248.41,2158.77],[213.78,2158.95],[213.69,2094.25],[248.33,2094.34]],
      "area": "66 m²",
      "estado": "Disponible"
    },
    {
      "id": "H-37",
      "coords": [[249.47,2158.86],[284.08,2158.86],[284.26,2094.33],[249.45,2094.24]],
      "area": "66 m²",
      "estado": "Disponible"
    },
    {
      "id": "H-38",
      "coords": [[285.33,2094.33],[319.79,2094.42],[319.97,2158.77],[285.16,2158.94]],
      "area": "66 m²",
      "estado": "Disponible"
    },
    {
      "id": "H-39",
      "coords": [[355.93,2094.16],[356.02,2158.77],[321.12,2158.94],[321.03,2094.42]],
      "area": "66 m²",
      "estado": "Disponible"
    },
    {
      "id": "H-40",
      "coords": [[391.82,2094.33],[391.82,2158.68],[357.1,2158.86],[356.92,2094.33]],
      "area": "66 m²",
      "estado": "Disponible"
    },
    {
      "id": "H-41",
      "coords": [[427.45,2094.42],[427.62,2158.77],[392.81,2158.86],[392.63,2094.07]],
      "area": "66 m²",
      "estado": "Disponible"
    },
    {
      "id": "H-42",
      "coords": [[463.42,2094.16],[463.42,2158.94],[428.7,2159.03],[428.7,2094.33]],
      "area": "66 m²",
      "estado": "Disponible"
    },
    {
      "id": "H-43",
      "coords": [[464.49,2093.98],[464.49,2158.94],[499.3,2158.86],[499.22,2094.24]],
      "area": "66 m²",
      "estado": "Disponible"
    },
    {
      "id": "H-44",
      "coords": [[500.21,2094.24],[535.02,2094.24],[534.84,2158.86],[500.21,2158.94]],
      "area": "66 m²",
      "estado": "Disponible"
    },
    {
      "id": "H-45",
      "coords": [[188.71,2082.75],[188.8,2117.31],[118.3,2117.31],[118.12,2082.49]],
      "area": "66 m²",
      "estado": "Disponible"
    },
    {
      "id": "H-46",
      "coords": [[188.71,2118.29],[188.89,2153.02],[118.3,2153.02],[118.12,2118.29]],
      "area": "66 m²",
      "estado": "Disponible"
    },
    {
      "id": "H-47",
      "coords": [[188.72,2154.08],[188.72,2189],[118.3,2188.82],[118.21,2154.17]],
      "area": "66 m²",
      "estado": "Disponible"
    },
    {
      "id": "H-48",
      "coords": [[188.63,2189.97],[188.71,2224.53],[118.3,2224.53],[118.03,2189.88]],
      "area": "66 m²",
      "estado": "Disponible"
    },
    {
      "id": "H-49",
      "coords": [[117.05,2189.79],[117.23,2224.62],[46.55,2224.62],[46.46,2189.88]],
      "area": "66 m²",
      "estado": "Disponible"
    },
    {
      "id": "H-50",
      "coords": [[117.03,2154.17],[117.12,2188.73],[46.44,2188.82],[46.44,2154.08]],
      "area": "66 m²",
      "estado": "Disponible"
    },
    {
      "id": "H-51",
      "coords": [[117.12,2118.29],[117.12,2153.11],[46.53,2153.11],[46.53,2118.29]],
      "area": "66 m²",
      "estado": "Disponible"
    },
    {
      "id": "H-52",
      "coords": [[117.09,2082.5],[117.18,2117.32],[46.38,2117.32],[46.47,2082.41]],
      "area": "66 m²",
      "estado": "Disponible"
    },
    {
      "id": "H-53",
      "coords": [[117.09,2011.51],[117.18,2046.07],[46.48,2046.25],[46.48,2011.34]],
      "area": "66 m²",
      "estado": "Disponible"
    },
    {
      "id": "H-54",
      "coords": [[117,1975.72],[117.18,2010.28],[46.41,2010.28],[46.5,1975.54]],
      "area": "66 m²",
      "estado": "Disponible"
    },
    {
      "id": "H-55",
      "coords": [[117.18,1939.92],[117.09,1974.39],[46.41,1974.48],[46.41,1939.92]],
      "area": "66 m²",
      "estado": "Disponible"
    },
    {
      "id": "H-56",
      "coords": [[117.09,1904.3],[117.18,1938.59],[46.5,1938.77],[46.5,1904.12]],
      "area": "66 m²",
      "estado": "Disponible"
    },
    {
      "id": "H-57",
      "coords": [[117.21,1903.01],[117.13,1868.45],[46.56,1868.41],[46.48,1902.88]],
      "area": "66 m²",
      "estado": "Disponible"
    },
    {
      "id": "H-58",
      "coords": [[117,1832.7],[117.18,1867.26],[46.5,1867.17],[46.41,1832.61]],
      "area": "66 m²",
      "estado": "Disponible"
    },
    {
      "id": "H-59",
      "coords": [[46.39,1831.47],[46.39,1796.64],[117.09,1796.46],[117.18,1831.55]],
      "area": "66 m²",
      "estado": "Disponible"
    },
    {
      "id": "H-60",
      "coords": [[188.77,1796.64],[188.77,1831.47],[118.34,1831.47],[117.99,1796.46]],
      "area": "66 m²",
      "estado": "Disponible"
    },
    {
      "id": "H-61",
      "coords": [[188.68,1832.61],[188.77,1867.26],[118.16,1867.26],[118.16,1832.61]],
      "area": "66 m²",
      "estado": "Disponible"
    },
    {
      "id": "H-62",
      "coords": [[188.69,1868.41],[188.78,1902.97],[118.24,1903.06],[118.16,1868.32]],
      "area": "66 m²",
      "estado": "Disponible"
    },
    {
      "id": "H-63",
      "coords": [[188.69,1904.12],[188.78,1938.77],[118.16,1938.77],[118.25,1904.03]],
      "area": "66 m²",
      "estado": "Disponible"
    },
    {
      "id": "H-64",
      "coords": [[188.79,1939.83],[188.79,1974.65],[118.25,1974.48],[118.07,1939.74]],
      "area": "66 m²",
      "estado": "Disponible"
    },
    {
      "id": "H-65",
      "coords": [[188.68,1975.63],[188.68,2010.28],[118.25,2010.36],[118.07,1975.63]],
      "area": "66 m²",
      "estado": "Disponible"
    },
    {
      "id": "H-66",
      "coords": [[188.59,2011.42],[188.76,2046.25],[118.16,2046.25],[117.98,2011.34]],
      "area": "66 m²",
      "estado": "Disponible"
    },
    {
      "id": "H-67",
      "coords": [[248.34,1987.56],[248.52,2051.99],[213.71,2051.99],[213.53,1987.56]],
      "area": "66 m²",
      "estado": "Disponible"
    },
    {
      "id": "H-68",
      "coords": [[249.42,1987.47],[249.51,2052.17],[284.14,2052.08],[284.14,1987.47]],
      "area": "66 m²",
      "estado": "Disponible"
    },
    {
      "id": "H-69",
      "coords": [[326.13,1987.47],[285.22,1987.47],[285.21,2052.08],[326.04,2051.99]],
      "area": "66 m²",
      "estado": "Disponible"
    },
    {
      "id": "H-70",
      "coords": [[386.85,1987.47],[386.76,2052.17],[427.49,2051.91],[427.58,1987.56]],
      "area": "66 m²",
      "estado": "Disponible"
    },
    {
      "id": "H-71",
      "coords": [[428.58,1987.47],[463.48,1987.47],[463.48,2052.17],[428.58,2052.08]],
      "area": "66 m²",
      "estado": "Disponible"
    },
    {
      "id": "H-72",
      "coords": [[464.47,1987.56],[464.29,2052.44],[499.1,2051.99],[499.1,1987.65]],
      "area": "66 m²",
      "estado": "Disponible"
    },
    {
      "id": "H-73",
      "coords": [[499.1,1951.76],[499.28,1986.76],[434.64,1986.58],[434.55,1951.76]],
      "area": "66 m²",
      "estado": "Disponible"
    },
    {
      "id": "H-74",
      "coords": [[433.59,1951.94],[433.51,1986.41],[368.82,1986.5],[368.82,1951.76]],
      "area": "66 m²",
      "estado": "Disponible"
    },
    {
      "id": "H-75",
      "coords": [[344.11,1951.7],[344.02,1986.44],[279.46,1986.59],[279.29,1951.67]],
      "area": "66 m²",
      "estado": "Disponible"
    },
    {
      "id": "H-76",
      "coords": [[278.3,1951.82],[278.3,1986.47],[213.71,1986.5],[213.53,1951.67]],
      "area": "66 m²",
      "estado": "Disponible"
    },
    {
      "id": "H-77",
      "coords": [[248.43,1862.31],[248.43,1926.66],[213.71,1927.01],[213.61,1862.22]],
      "area": "66 m²",
      "estado": "Disponible"
    },
    {
      "id": "H-78",
      "coords": [[249.42,1862.31],[284.23,1862.22],[284.23,1926.84],[249.42,1926.92]],
      "area": "66 m²",
      "estado": "Disponible"
    },
    {
      "id": "H-79",
      "coords": [[319.94,1862.4],[319.94,1926.75],[285.3,1926.84],[285.22,1862.22]],
      "area": "66 m²",
      "estado": "Disponible"
    },
    {
      "id": "H-80",
      "coords": [[355.99,1862.22],[355.73,1926.75],[321.18,1926.92],[321.01,1862.22]],
      "area": "66 m²",
      "estado": "Disponible"
    },
    {
      "id": "H-81",
      "coords": [[391.8,1862.4],[391.62,1926.84],[356.99,1926.75],[356.9,1862.22]],
      "area": "66 m²",
      "estado": "Disponible"
    },
    {
      "id": "H-82",
      "coords": [[427.51,1862.22],[392.7,1862.31],[392.7,1926.92],[427.6,1926.75]],
      "area": "66 m²",
      "estado": "Disponible"
    },
    {
      "id": "H-83",
      "coords": [[463.39,1862.31],[463.3,1926.75],[428.67,1926.92],[428.58,1862.22]],
      "area": "66 m²",
      "estado": "Disponible"
    },
    {
      "id": "H-84",
      "coords": [[499.1,1862.31],[499.19,1926.84],[464.55,1926.84],[464.46,1862.31]],
      "area": "66 m²",
      "estado": "Disponible"
    },
    {
      "id": "H-85",
      "coords": [[499.1,1796.74],[499.1,1861.18],[464.47,1861.36],[464.47,1796.48]],
      "area": "66 m²",
      "estado": "Disponible"
    },
    {
      "id": "H-86",
      "coords": [[463.32,1796.69],[463.5,1861.48],[428.69,1861.4],[428.51,1796.61]],
      "area": "66 m²",
      "estado": "Disponible"
    },
    {
      "id": "H-87",
      "coords": [[427.45,1796.61],[427.63,1861.31],[392.73,1861.4],[392.82,1796.52]],
      "area": "66 m²",
      "estado": "Disponible"
    },
    {
      "id": "H-88",
      "coords": [[391.67,1796.69],[391.76,1861.4],[357.03,1861.4],[356.86,1796.52]],
      "area": "66 m²",
      "estado": "Disponible"
    },
    {
      "id": "H-89",
      "coords": [[355.83,1796.82],[355.92,1861.34],[321.11,1861.43],[321.02,1796.46]],
      "area": "66 m²",
      "estado": "Disponible"
    },
    {
      "id": "H-90",
      "coords": [[320.04,1796.64],[320.13,1861.25],[285.32,1861.52],[285.32,1796.55]],
      "area": "66 m²",
      "estado": "Disponible"
    },
    {
      "id": "H-91",
      "coords": [[284.15,1796.73],[284.23,1861.34],[249.51,1861.34],[249.51,1796.55]],
      "area": "66 m²",
      "estado": "Disponible"
    },
    {
      "id": "H-92",
      "coords": [[248.36,1796.64],[248.53,1861.43],[213.63,1861.34],[213.63,1796.55]],
      "area": "66 m²",
      "estado": "Disponible"
    }
    ,
    {
      "id": "H-93",
      "coords": [[622.06,1905.44],[621.97,1940.09],[551.38,1940.17],[551.47,1905.26]],
      "area": "66 m²",
      "estado": "Disponible"
    },
    {
      "id": "H-94",
      "coords": [[551.35,1869.47],[551.44,1904.3],[621.94,1904.21],[622.03,1869.56]],
      "area": "66 m²",
      "estado": "Disponible"
    },
    {
      "id": "H-95",
      "coords": [[586.17,1868.41],[551.45,1868.59],[551.45,1798.05],[586.08,1798.05]],
      "area": "66 m²",
      "estado": "Disponible"
    },
    {
      "id": "H-96",
      "coords": [[622.14,1797.88],[621.97,1868.5],[587.24,1868.41],[587.15,1797.97]],
      "area": "66 m²",
      "estado": "Disponible"
    },
    {
      "id": "H-97",
      "coords": [[657.85,1797.97],[657.94,1868.41],[623.12,1868.41],[622.94,1797.97]],
      "area": "66 m²",
      "estado": "Disponible"
    },
    {
      "id": "H-98",
      "coords": [[693.91,1798.05],[693.47,1868.32],[659.1,1868.5],[659.01,1797.88]],
      "area": "66 m²",
      "estado": "Disponible"
    },
    {
      "id": "H-99",
      "coords": [[693.56,1869.56],[693.73,1904.21],[623.12,1904.3],[623.03,1869.47]],
      "area": "66 m²",
      "estado": "Disponible"
    },
    {
      "id": "H-100",
      "coords": [[623.06,1905.26],[623.06,1940.17],[693.64,1940.01],[693.73,1905.36]],
      "area": "66 m²",
      "estado": "Disponible"
    }
]

